balparda_baselib/__init__.py
balparda_baselib/base.py
balparda_baselib/bin_fernet.py
balparda_baselib/py.typed
balparda_baselib-1.11.dist-info/licenses/LICENSE
balparda_baselib-1.11.dist-info/METADATA
balparda_baselib-1.11.dist-info/WHEEL
balparda_baselib-1.11.dist-info/top_level.txt
balparda_baselib-1.11.dist-info/RECORD
