Metadata-Version: 2.4
Name: balparda_baselib
Version: 1.11
Summary: A base library for various utilities, by balparda@github.com
Author-email: Daniel Balparda <balparda@github.com>
License-Expression: Apache-2.0
Project-URL: Homepage, https://github.com/balparda/baselib
Project-URL: PyPI, https://pypi.org/project/balparda_baselib/
Classifier: Programming Language :: Python :: 3
Classifier: Programming Language :: Python :: 3.11
Classifier: Programming Language :: Python :: 3.12
Classifier: Programming Language :: Python :: 3.13
Classifier: Operating System :: OS Independent
Classifier: Topic :: Utilities
Classifier: Topic :: Security :: Cryptography
Requires-Python: >=3.11.13
License-File: LICENSE
Requires-Dist: cryptography>=41.0.7
Requires-Dist: Pillow>=10.2
Dynamic: license-file
